LICENSE
MANIFEST.in
README.rst
epydoc-config
ez_setup.py
setup.py
mongobongo/__init__.py
mongobongo/attributed.py
mongobongo/document.py
pymongo_bongo.egg-info/PKG-INFO
pymongo_bongo.egg-info/SOURCES.txt
pymongo_bongo.egg-info/dependency_links.txt
pymongo_bongo.egg-info/top_level.txt
test/__init__.py
test/test_attributed.py
test/test_document.py