Metadata-Version: 1.0
Name: pymongo-bongo
Version: 0.1.3
Summary: Sytax sugar for PyMongo and MongoDB <http://www.mongodb.org>
Home-page: http://github.com/svetlyak40wt/pymongo-bongo/
Author: Alexander Artemenko
Author-email: svetlyak.40wt@gmail.com
License: New BSD License
Platform: UNKNOWN
Classifier: Development Status :: 4 - Beta
Classifier: Intended Audience :: Developers
Classifier: License :: OSI Approved :: BSD License
Classifier: Operating System :: MacOS :: MacOS X
Classifier: Operating System :: Microsoft :: Windows
Classifier: Operating System :: POSIX
Classifier: Programming Language :: Python
Classifier: Topic :: Database
